{
  "records": [
    {
      "decision_id": "REL-53b297bb7b0a9e6a",
      "finding_id": "FND-CONTAINER-026cbd40a3d8",
      "matched_release_rule_ids": [
        "RG-COND-001"
      ],
      "policy_version": "1.0",
      "release_decision": "conditional_pass",
      "release_impact": "conditional_pass",
      "required_actions": [
        "Track upstream fix availability and rebuild the image when a fix is published."
      ],
      "required_approvals": [
        "Product Security",
        "Technical Owner"
      ]
    },
    {
      "decision_id": "REL-53b297bb7b0a9e6a",
      "finding_id": "FND-CONTAINER-033201244a2b",
      "matched_release_rule_ids": [
        "RG-COND-001"
      ],
      "policy_version": "1.0",
      "release_decision": "conditional_pass",
      "release_impact": "conditional_pass",
      "required_actions": [
        "Track upstream fix availability and rebuild the image when a fix is published."
      ],
      "required_approvals": [
        "Product Security",
        "Technical Owner"
      ]
    },
    {
      "decision_id": "REL-53b297bb7b0a9e6a",
      "finding_id": "FND-CONTAINER-35a70101ee98",
      "matched_release_rule_ids": [
        "RG-COND-001"
      ],
      "policy_version": "1.0",
      "release_decision": "conditional_pass",
      "release_impact": "conditional_pass",
      "required_actions": [
        "Track upstream fix availability and rebuild the image when a fix is published."
      ],
      "required_approvals": [
        "Product Security",
        "Technical Owner"
      ]
    },
    {
      "decision_id": "REL-53b297bb7b0a9e6a",
      "finding_id": "FND-CONTAINER-35a7a61eb9e3",
      "matched_release_rule_ids": [
        "RG-COND-001"
      ],
      "policy_version": "1.0",
      "release_decision": "conditional_pass",
      "release_impact": "conditional_pass",
      "required_actions": [
        "Track upstream fix availability and rebuild the image when a fix is published."
      ],
      "required_approvals": [
        "Product Security",
        "Technical Owner"
      ]
    },
    {
      "decision_id": "REL-53b297bb7b0a9e6a",
      "finding_id": "FND-CONTAINER-3686ad447a1f",
      "matched_release_rule_ids": [
        "RG-COND-001"
      ],
      "policy_version": "1.0",
      "release_decision": "conditional_pass",
      "release_impact": "conditional_pass",
      "required_actions": [
        "Track upstream fix availability and rebuild the image when a fix is published."
      ],
      "required_approvals": [
        "Product Security",
        "Technical Owner"
      ]
    },
    {
      "decision_id": "REL-53b297bb7b0a9e6a",
      "finding_id": "FND-CONTAINER-4a39d4c85743",
      "matched_release_rule_ids": [
        "RG-COND-001"
      ],
      "policy_version": "1.0",
      "release_decision": "conditional_pass",
      "release_impact": "conditional_pass",
      "required_actions": [
        "Track upstream fix availability and rebuild the image when a fix is published."
      ],
      "required_approvals": [
        "Product Security",
        "Technical Owner"
      ]
    },
    {
      "decision_id": "REL-53b297bb7b0a9e6a",
      "finding_id": "FND-CONTAINER-57b96cf12bee",
      "matched_release_rule_ids": [
        "RG-COND-001"
      ],
      "policy_version": "1.0",
      "release_decision": "conditional_pass",
      "release_impact": "conditional_pass",
      "required_actions": [
        "Track upstream fix availability and rebuild the image when a fix is published."
      ],
      "required_approvals": [
        "Product Security",
        "Technical Owner"
      ]
    },
    {
      "decision_id": "REL-53b297bb7b0a9e6a",
      "finding_id": "FND-CONTAINER-5ee1761422cc",
      "matched_release_rule_ids": [
        "RG-COND-001"
      ],
      "policy_version": "1.0",
      "release_decision": "conditional_pass",
      "release_impact": "conditional_pass",
      "required_actions": [
        "Track upstream fix availability and rebuild the image when a fix is published."
      ],
      "required_approvals": [
        "Product Security",
        "Technical Owner"
      ]
    },
    {
      "decision_id": "REL-53b297bb7b0a9e6a",
      "finding_id": "FND-CONTAINER-6017bcc173f8",
      "matched_release_rule_ids": [
        "RG-COND-001"
      ],
      "policy_version": "1.0",
      "release_decision": "conditional_pass",
      "release_impact": "conditional_pass",
      "required_actions": [
        "Track upstream fix availability and rebuild the image when a fix is published."
      ],
      "required_approvals": [
        "Product Security",
        "Technical Owner"
      ]
    },
    {
      "decision_id": "REL-53b297bb7b0a9e6a",
      "finding_id": "FND-CONTAINER-6884a6a2aeb3",
      "matched_release_rule_ids": [
        "RG-COND-001"
      ],
      "policy_version": "1.0",
      "release_decision": "conditional_pass",
      "release_impact": "conditional_pass",
      "required_actions": [
        "Track upstream fix availability and rebuild the image when a fix is published."
      ],
      "required_approvals": [
        "Product Security",
        "Technical Owner"
      ]
    },
    {
      "decision_id": "REL-53b297bb7b0a9e6a",
      "finding_id": "FND-CONTAINER-77763b149b4f",
      "matched_release_rule_ids": [
        "RG-COND-001"
      ],
      "policy_version": "1.0",
      "release_decision": "conditional_pass",
      "release_impact": "conditional_pass",
      "required_actions": [
        "Track upstream fix availability and rebuild the image when a fix is published."
      ],
      "required_approvals": [
        "Product Security",
        "Technical Owner"
      ]
    },
    {
      "decision_id": "REL-53b297bb7b0a9e6a",
      "finding_id": "FND-CONTAINER-9360fa554791",
      "matched_release_rule_ids": [
        "RG-COND-001"
      ],
      "policy_version": "1.0",
      "release_decision": "conditional_pass",
      "release_impact": "conditional_pass",
      "required_actions": [
        "Track upstream fix availability and rebuild the image when a fix is published."
      ],
      "required_approvals": [
        "Product Security",
        "Technical Owner"
      ]
    },
    {
      "decision_id": "REL-53b297bb7b0a9e6a",
      "finding_id": "FND-CONTAINER-95a38a1f2a20",
      "matched_release_rule_ids": [
        "RG-COND-001"
      ],
      "policy_version": "1.0",
      "release_decision": "conditional_pass",
      "release_impact": "conditional_pass",
      "required_actions": [
        "Track upstream fix availability and rebuild the image when a fix is published."
      ],
      "required_approvals": [
        "Product Security",
        "Technical Owner"
      ]
    },
    {
      "decision_id": "REL-53b297bb7b0a9e6a",
      "finding_id": "FND-CONTAINER-96b263718199",
      "matched_release_rule_ids": [
        "RG-COND-001"
      ],
      "policy_version": "1.0",
      "release_decision": "conditional_pass",
      "release_impact": "conditional_pass",
      "required_actions": [
        "Track upstream fix availability and rebuild the image when a fix is published."
      ],
      "required_approvals": [
        "Product Security",
        "Technical Owner"
      ]
    },
    {
      "decision_id": "REL-53b297bb7b0a9e6a",
      "finding_id": "FND-CONTAINER-9bac41a1b5ac",
      "matched_release_rule_ids": [
        "RG-COND-001"
      ],
      "policy_version": "1.0",
      "release_decision": "conditional_pass",
      "release_impact": "conditional_pass",
      "required_actions": [
        "Track upstream fix availability and rebuild the image when a fix is published."
      ],
      "required_approvals": [
        "Product Security",
        "Technical Owner"
      ]
    },
    {
      "decision_id": "REL-53b297bb7b0a9e6a",
      "finding_id": "FND-CONTAINER-b26883cf2982",
      "matched_release_rule_ids": [
        "RG-COND-001"
      ],
      "policy_version": "1.0",
      "release_decision": "conditional_pass",
      "release_impact": "conditional_pass",
      "required_actions": [
        "Track upstream fix availability and rebuild the image when a fix is published."
      ],
      "required_approvals": [
        "Product Security",
        "Technical Owner"
      ]
    },
    {
      "decision_id": "REL-53b297bb7b0a9e6a",
      "finding_id": "FND-CONTAINER-ba223b9333c9",
      "matched_release_rule_ids": [
        "RG-COND-001"
      ],
      "policy_version": "1.0",
      "release_decision": "conditional_pass",
      "release_impact": "conditional_pass",
      "required_actions": [
        "Track upstream fix availability and rebuild the image when a fix is published."
      ],
      "required_approvals": [
        "Product Security",
        "Technical Owner"
      ]
    },
    {
      "decision_id": "REL-53b297bb7b0a9e6a",
      "finding_id": "FND-CONTAINER-c118af042a95",
      "matched_release_rule_ids": [
        "RG-COND-001"
      ],
      "policy_version": "1.0",
      "release_decision": "conditional_pass",
      "release_impact": "conditional_pass",
      "required_actions": [
        "Track upstream fix availability and rebuild the image when a fix is published."
      ],
      "required_approvals": [
        "Product Security",
        "Technical Owner"
      ]
    },
    {
      "decision_id": "REL-53b297bb7b0a9e6a",
      "finding_id": "FND-CONTAINER-c1e6ced9904f",
      "matched_release_rule_ids": [
        "RG-COND-001"
      ],
      "policy_version": "1.0",
      "release_decision": "conditional_pass",
      "release_impact": "conditional_pass",
      "required_actions": [
        "Track upstream fix availability and rebuild the image when a fix is published."
      ],
      "required_approvals": [
        "Product Security",
        "Technical Owner"
      ]
    },
    {
      "decision_id": "REL-53b297bb7b0a9e6a",
      "finding_id": "FND-CONTAINER-c7563eb73df0",
      "matched_release_rule_ids": [
        "RG-COND-001"
      ],
      "policy_version": "1.0",
      "release_decision": "conditional_pass",
      "release_impact": "conditional_pass",
      "required_actions": [
        "Track upstream fix availability and rebuild the image when a fix is published."
      ],
      "required_approvals": [
        "Product Security",
        "Technical Owner"
      ]
    },
    {
      "decision_id": "REL-53b297bb7b0a9e6a",
      "finding_id": "FND-CONTAINER-d0df15bb32ed",
      "matched_release_rule_ids": [
        "RG-COND-001"
      ],
      "policy_version": "1.0",
      "release_decision": "conditional_pass",
      "release_impact": "conditional_pass",
      "required_actions": [
        "Track upstream fix availability and rebuild the image when a fix is published."
      ],
      "required_approvals": [
        "Product Security",
        "Technical Owner"
      ]
    },
    {
      "decision_id": "REL-53b297bb7b0a9e6a",
      "finding_id": "FND-CONTAINER-ef0f3e5e6558",
      "matched_release_rule_ids": [
        "RG-COND-001"
      ],
      "policy_version": "1.0",
      "release_decision": "conditional_pass",
      "release_impact": "conditional_pass",
      "required_actions": [
        "Track upstream fix availability and rebuild the image when a fix is published."
      ],
      "required_approvals": [
        "Product Security",
        "Technical Owner"
      ]
    },
    {
      "decision_id": "REL-53b297bb7b0a9e6a",
      "finding_id": "FND-DAST-7f68e8fb688f",
      "matched_release_rule_ids": [
        "RG-WARN-002"
      ],
      "policy_version": "1.0",
      "release_decision": "conditional_pass",
      "release_impact": "warn",
      "required_actions": [
        "Review during normal maintenance."
      ],
      "required_approvals": []
    },
    {
      "decision_id": "REL-53b297bb7b0a9e6a",
      "finding_id": "FND-DAST-e607d905531a",
      "matched_release_rule_ids": [
        "RG-WARN-002"
      ],
      "policy_version": "1.0",
      "release_decision": "conditional_pass",
      "release_impact": "warn",
      "required_actions": [
        "Review during normal maintenance."
      ],
      "required_approvals": []
    },
    {
      "decision_id": "REL-53b297bb7b0a9e6a",
      "finding_id": "FND-SECUREDESI-0e84d1c52550",
      "matched_release_rule_ids": [
        "RG-WARN-001"
      ],
      "policy_version": "1.0",
      "release_decision": "conditional_pass",
      "release_impact": "warn",
      "required_actions": [
        "Track remediation within SLA."
      ],
      "required_approvals": []
    },
    {
      "decision_id": "REL-53b297bb7b0a9e6a",
      "finding_id": "FND-SECUREDESI-17c88481ce5d",
      "matched_release_rule_ids": [
        "RG-WARN-001"
      ],
      "policy_version": "1.0",
      "release_decision": "conditional_pass",
      "release_impact": "warn",
      "required_actions": [
        "Track remediation within SLA."
      ],
      "required_approvals": []
    },
    {
      "decision_id": "REL-53b297bb7b0a9e6a",
      "finding_id": "FND-SECUREDESI-667c88d66538",
      "matched_release_rule_ids": [
        "RG-WARN-001"
      ],
      "policy_version": "1.0",
      "release_decision": "conditional_pass",
      "release_impact": "warn",
      "required_actions": [
        "Track remediation within SLA."
      ],
      "required_approvals": []
    },
    {
      "decision_id": "REL-53b297bb7b0a9e6a",
      "finding_id": "FND-SECUREDESI-77c7990be9b8",
      "matched_release_rule_ids": [
        "RG-WARN-001"
      ],
      "policy_version": "1.0",
      "release_decision": "conditional_pass",
      "release_impact": "warn",
      "required_actions": [
        "Track remediation within SLA."
      ],
      "required_approvals": []
    },
    {
      "decision_id": "REL-53b297bb7b0a9e6a",
      "finding_id": "FND-SECUREDESI-ac50e3235345",
      "matched_release_rule_ids": [
        "RG-WARN-001"
      ],
      "policy_version": "1.0",
      "release_decision": "conditional_pass",
      "release_impact": "warn",
      "required_actions": [
        "Track remediation within SLA."
      ],
      "required_approvals": []
    },
    {
      "decision_id": "REL-53b297bb7b0a9e6a",
      "finding_id": "FND-SECUREDESI-e7cd910bd1f6",
      "matched_release_rule_ids": [
        "RG-WARN-001"
      ],
      "policy_version": "1.0",
      "release_decision": "conditional_pass",
      "release_impact": "warn",
      "required_actions": [
        "Track remediation within SLA."
      ],
      "required_approvals": []
    },
    {
      "decision_id": "REL-53b297bb7b0a9e6a",
      "finding_id": "FND-SUPPRESSIO-1065083a8d4b",
      "matched_release_rule_ids": [
        "RG-COND-002",
        "RG-COND-003"
      ],
      "policy_version": "1.0",
      "release_decision": "conditional_pass",
      "release_impact": "conditional_pass",
      "required_actions": [
        "Review reference infrastructure control before production deployment.",
        "Review the suppression before expiry and keep compensating controls current."
      ],
      "required_approvals": [
        "Cloud Security",
        "Product Security",
        "Risk Owner"
      ]
    },
    {
      "decision_id": "REL-53b297bb7b0a9e6a",
      "finding_id": "FND-SUPPRESSIO-47693ff859ed",
      "matched_release_rule_ids": [
        "RG-COND-002",
        "RG-COND-003"
      ],
      "policy_version": "1.0",
      "release_decision": "conditional_pass",
      "release_impact": "conditional_pass",
      "required_actions": [
        "Review reference infrastructure control before production deployment.",
        "Review the suppression before expiry and keep compensating controls current."
      ],
      "required_approvals": [
        "Cloud Security",
        "Product Security",
        "Risk Owner"
      ]
    },
    {
      "decision_id": "REL-53b297bb7b0a9e6a",
      "finding_id": "FND-SUPPRESSIO-65201925e5c5",
      "matched_release_rule_ids": [
        "RG-COND-002",
        "RG-COND-003"
      ],
      "policy_version": "1.0",
      "release_decision": "conditional_pass",
      "release_impact": "conditional_pass",
      "required_actions": [
        "Review reference infrastructure control before production deployment.",
        "Review the suppression before expiry and keep compensating controls current."
      ],
      "required_approvals": [
        "Cloud Security",
        "Product Security",
        "Risk Owner"
      ]
    },
    {
      "decision_id": "REL-53b297bb7b0a9e6a",
      "finding_id": "FND-SUPPRESSIO-68e51d21b290",
      "matched_release_rule_ids": [
        "RG-COND-002",
        "RG-COND-003"
      ],
      "policy_version": "1.0",
      "release_decision": "conditional_pass",
      "release_impact": "conditional_pass",
      "required_actions": [
        "Review reference infrastructure control before production deployment.",
        "Review the suppression before expiry and keep compensating controls current."
      ],
      "required_approvals": [
        "Cloud Security",
        "Product Security",
        "Risk Owner"
      ]
    },
    {
      "decision_id": "REL-53b297bb7b0a9e6a",
      "finding_id": "FND-SUPPRESSIO-6dce772b98c3",
      "matched_release_rule_ids": [
        "RG-COND-002",
        "RG-COND-003"
      ],
      "policy_version": "1.0",
      "release_decision": "conditional_pass",
      "release_impact": "conditional_pass",
      "required_actions": [
        "Review reference infrastructure control before production deployment.",
        "Review the suppression before expiry and keep compensating controls current."
      ],
      "required_approvals": [
        "Cloud Security",
        "Product Security",
        "Risk Owner"
      ]
    },
    {
      "decision_id": "REL-53b297bb7b0a9e6a",
      "finding_id": "FND-SUPPRESSIO-713bb8f041d7",
      "matched_release_rule_ids": [
        "RG-COND-002",
        "RG-COND-003"
      ],
      "policy_version": "1.0",
      "release_decision": "conditional_pass",
      "release_impact": "conditional_pass",
      "required_actions": [
        "Review reference infrastructure control before production deployment.",
        "Review the suppression before expiry and keep compensating controls current."
      ],
      "required_approvals": [
        "Cloud Security",
        "Product Security",
        "Risk Owner"
      ]
    },
    {
      "decision_id": "REL-53b297bb7b0a9e6a",
      "finding_id": "FND-SUPPRESSIO-7b3ddcaa6af8",
      "matched_release_rule_ids": [
        "RG-COND-002",
        "RG-COND-003"
      ],
      "policy_version": "1.0",
      "release_decision": "conditional_pass",
      "release_impact": "conditional_pass",
      "required_actions": [
        "Review reference infrastructure control before production deployment.",
        "Review the suppression before expiry and keep compensating controls current."
      ],
      "required_approvals": [
        "Cloud Security",
        "Product Security",
        "Risk Owner"
      ]
    },
    {
      "decision_id": "REL-53b297bb7b0a9e6a",
      "finding_id": "FND-SUPPRESSIO-836cb2a2770d",
      "matched_release_rule_ids": [
        "RG-COND-002"
      ],
      "policy_version": "1.0",
      "release_decision": "conditional_pass",
      "release_impact": "conditional_pass",
      "required_actions": [
        "Review the suppression before expiry and keep compensating controls current."
      ],
      "required_approvals": [
        "Product Security"
      ]
    },
    {
      "decision_id": "REL-53b297bb7b0a9e6a",
      "finding_id": "FND-SUPPRESSIO-8632c434b354",
      "matched_release_rule_ids": [
        "RG-COND-002",
        "RG-COND-003"
      ],
      "policy_version": "1.0",
      "release_decision": "conditional_pass",
      "release_impact": "conditional_pass",
      "required_actions": [
        "Review reference infrastructure control before production deployment.",
        "Review the suppression before expiry and keep compensating controls current."
      ],
      "required_approvals": [
        "Cloud Security",
        "Product Security",
        "Risk Owner"
      ]
    },
    {
      "decision_id": "REL-53b297bb7b0a9e6a",
      "finding_id": "FND-SUPPRESSIO-974e196f7185",
      "matched_release_rule_ids": [
        "RG-COND-002"
      ],
      "policy_version": "1.0",
      "release_decision": "conditional_pass",
      "release_impact": "conditional_pass",
      "required_actions": [
        "Review the suppression before expiry and keep compensating controls current."
      ],
      "required_approvals": [
        "Product Security"
      ]
    },
    {
      "decision_id": "REL-53b297bb7b0a9e6a",
      "finding_id": "FND-SUPPRESSIO-b5c9f1d0aae2",
      "matched_release_rule_ids": [
        "RG-COND-002",
        "RG-COND-003"
      ],
      "policy_version": "1.0",
      "release_decision": "conditional_pass",
      "release_impact": "conditional_pass",
      "required_actions": [
        "Review reference infrastructure control before production deployment.",
        "Review the suppression before expiry and keep compensating controls current."
      ],
      "required_approvals": [
        "Cloud Security",
        "Product Security",
        "Risk Owner"
      ]
    },
    {
      "decision_id": "REL-53b297bb7b0a9e6a",
      "finding_id": "FND-SUPPRESSIO-d403fca790bf",
      "matched_release_rule_ids": [
        "RG-COND-002",
        "RG-COND-003"
      ],
      "policy_version": "1.0",
      "release_decision": "conditional_pass",
      "release_impact": "conditional_pass",
      "required_actions": [
        "Review reference infrastructure control before production deployment.",
        "Review the suppression before expiry and keep compensating controls current."
      ],
      "required_approvals": [
        "Cloud Security",
        "Product Security",
        "Risk Owner"
      ]
    },
    {
      "decision_id": "REL-53b297bb7b0a9e6a",
      "finding_id": "FND-SUPPRESSIO-e0d3613118cd",
      "matched_release_rule_ids": [
        "RG-COND-002",
        "RG-COND-003"
      ],
      "policy_version": "1.0",
      "release_decision": "conditional_pass",
      "release_impact": "conditional_pass",
      "required_actions": [
        "Review reference infrastructure control before production deployment.",
        "Review the suppression before expiry and keep compensating controls current."
      ],
      "required_approvals": [
        "Cloud Security",
        "Product Security",
        "Risk Owner"
      ]
    },
    {
      "decision_id": "REL-53b297bb7b0a9e6a",
      "finding_id": "FND-SUPPRESSIO-f1fb6d611749",
      "matched_release_rule_ids": [
        "RG-COND-002",
        "RG-COND-003"
      ],
      "policy_version": "1.0",
      "release_decision": "conditional_pass",
      "release_impact": "conditional_pass",
      "required_actions": [
        "Review reference infrastructure control before production deployment.",
        "Review the suppression before expiry and keep compensating controls current."
      ],
      "required_approvals": [
        "Cloud Security",
        "Product Security",
        "Risk Owner"
      ]
    }
  ],
  "schema_version": "1.0"
}
